LICENSE
MANIFEST.in
NOTICES
setup.py
genie_ext/__init__.py
genie_ext/libs/conf/device/__init__.py
genie_ext/libs/conf/device/iosxe/device.py
genie_ext/libs/conf/device/junos/__init__.py
genie_ext/libs/conf/device/junos/device.py
samples/__init__.py
samples/bgp_routes_stability.py
samples/bgp_routes_stability.yaml
samples/router_bgp.py
samples/router_bgp.yaml
samples/router_forwarding.py
samples/router_forwarding.yaml
samples/samples.robot
samples/testbed_lab/lab_config.yaml
samples/testbed_lab/testbed_map.py
samples/testbed_templates/2stc_1router_type01.yaml
samples/testbed_templates/stc_portlist_bgp_routes_stability.yaml
script/__init__.py
script/check_stc_param.py
script/resources.robot
script/runtest.py
script/test_wrapper.py
script/testcase_schema_v1.json
spirent_testpack_framework.egg-info/PKG-INFO
spirent_testpack_framework.egg-info/SOURCES.txt
spirent_testpack_framework.egg-info/dependency_links.txt
spirent_testpack_framework.egg-info/top_level.txt
testbase/__init__.py
testbase/configutility.py
testbase/gen_testbed_config.py
testbase/settings.py
testbase/snedevice.py
testbase/snesession.py
testbase/spirent_logger.py
testbase/stcsession.py
testbase/testbase.py